fuzzy_context_finder/__init__.py
fuzzy_context_finder/keyword_context.py
fuzzy_context_finder-0.1.2.dist-info/LICENSE
fuzzy_context_finder-0.1.2.dist-info/METADATA
fuzzy_context_finder-0.1.2.dist-info/WHEEL
fuzzy_context_finder-0.1.2.dist-info/top_level.txt
fuzzy_context_finder-0.1.2.dist-info/RECORD
