Metadata-Version: 2.1
Name: fuzzy-context-finder
Version: 0.1.2
Summary: search for keywords and their context
Home-page: https://github.com/sandeepmj/fuzzy_context_finder
Author: Sandeep Junnarkar
Author-email: sjnews@gmail.com
License: UNKNOWN
Platform: UNKNOWN
Classifier: Programming Language :: Python :: 3
Classifier: License :: OSI Approved :: MIT License
Classifier: Operating System :: OS Independent
Requires-Python: >=3.7
License-File: LICENSE
Requires-Dist: regex
Requires-Dist: pandas (>=1.0.0)
Requires-Dist: rapidfuzz (>=2.0.0)
